showcase/__init__.py
showcase/arg_detector_io.py
showcase/constants.py
showcase/convert_word2vec_to_npz.py
showcase/eval.py
showcase/evaluate_end_to_end.py
showcase/get_vocab_from_word2vec.py
showcase/models.py
showcase/test.py
showcase/train.py
showcase/data/config.json
showcase/layer/__init__.py
showcase/layer/attention.py
showcase/layer/bi_gru.py
showcase/utils/__init__.py
showcase/utils/inputs.py
showcase/utils/outputs.py
showcase/utils/subfuncs.py
showcase_parser-0.0.1.dist-info/DESCRIPTION.rst
showcase_parser-0.0.1.dist-info/METADATA
showcase_parser-0.0.1.dist-info/RECORD
showcase_parser-0.0.1.dist-info/WHEEL
showcase_parser-0.0.1.dist-info/entry_points.txt
showcase_parser-0.0.1.dist-info/metadata.json
showcase_parser-0.0.1.dist-info/top_level.txt
