Metadata-Version: 2.0
Name: showcase-parser
Version: 0.0.1
Summary: Japanese Predicate-Argument Structure Analyzer
Home-page: https://github.com/cl-tohoku/showcase
Author: Yuichiroh Matsubayashi and Shun Kiyono
Author-email: y-matsu@ecei.tohoku.ac.jp
License: MIT License
Requires-Dist: logzero
Requires-Dist: numpy
Requires-Dist: torch (==0.4.0)
Requires-Dist: torchvision
Requires-Dist: tqdm
Provides-Extra: docs
Requires-Dist: commonmark (==0.5.4); extra == 'docs'
Requires-Dist: recommonmark; extra == 'docs'
Requires-Dist: sphinx; extra == 'docs'
Requires-Dist: sphinx-fontawesome; extra == 'docs'
Requires-Dist: sphinx-rtd-theme; extra == 'docs'
Provides-Extra: test
Requires-Dist: pytest; extra == 'test'
